chad/main.py
chad/utils/array.py
chad/utils/chad.py
chad/utils/config.py
chad/utils/cookie.py
chad/utils/directory.py
chad/utils/file.py
chad/utils/general.py
chad/utils/grep.py
chad/utils/proxy.py
chad/utils/validate.py
chad_extractor/main.py
chad_extractor/utils/array.py
chad_extractor/utils/config.py
chad_extractor/utils/directory.py
chad_extractor/utils/extractor.py
chad_extractor/utils/file.py
chad_extractor/utils/general.py
chad_extractor/utils/grep.py
chad_extractor/utils/input.py
chad_extractor/utils/jquery.py
chad_extractor/utils/report.py
chad_extractor/utils/result.py
chad_extractor/utils/storage.py
chad_extractor/utils/template.py
chad_extractor/utils/url.py
chad_extractor/utils/validate.py
dorks/social_media_dorks.txt
templates/social_media_template.json
google_chad-7.4.dist-info/METADATA
google_chad-7.4.dist-info/WHEEL
google_chad-7.4.dist-info/entry_points.txt
google_chad-7.4.dist-info/top_level.txt
google_chad-7.4.dist-info/RECORD
