Metadata-Version: 2.4
Name: google-chad
Version: 7.4
Summary: Not another Google Dorking tool.
Author: Ivan Sincek
Project-URL: Homepage, https://github.com/ivan-sincek/chad
Classifier: Programming Language :: Python :: 3
Classifier: License :: OSI Approved :: MIT License
Classifier: Operating System :: OS Independent
Requires-Python: >=3.10
Requires-Dist: alive-progress>=3.1.5
Requires-Dist: asyncio>=3.4.3
Requires-Dist: colorama>=0.4.6
Requires-Dist: python-dateutil>=2.9.0
Requires-Dist: nagooglesearch>=8.2
Requires-Dist: playwright>=1.47.0
Requires-Dist: regex>=2023.8.8
Requires-Dist: requests>=2.32.2
Requires-Dist: scrapy>=2.12.0
Requires-Dist: scrapy-playwright>=0.0.32
Requires-Dist: termcolor>=2.4.0
